docubleach/__init__.py
docubleach/bleach.py
docubleach-0.1.2.dist-info/entry_points.txt
docubleach-0.1.2.dist-info/LICENSE
docubleach-0.1.2.dist-info/METADATA
docubleach-0.1.2.dist-info/WHEEL
docubleach-0.1.2.dist-info/RECORD
