Metadata-Version: 2.1
Name: docubleach
Version: 0.1.2
Summary: Tool to purge and remove all macro and dynamic content from an MS Office file
License: MIT
Author: Patterbear
Requires-Python: >=3.11,<4.0
Classifier: License :: OSI Approved :: MIT License
Classifier: Programming Language :: Python :: 3
Classifier: Programming Language :: Python :: 3.11
Classifier: Programming Language :: Python :: 3.12
Requires-Dist: olefile (>=0.47,<0.48)
Requires-Dist: oletools (>=0.60.2,<0.61.0)
